Metadata-Version: 2.1
Name: xkcd2347
Version: 0.0.4
Summary: List the dependencies for a github project
Home-page: http://github.com/edsu/xkcd2347
Author: Ed Summers
Author-email: ehs@pobox.com
License: http://www.opensource.org/licenses/mit-license.php
Platform: UNKNOWN
